(0x00) nop		Not supported

(0x01) aconst_null	Not supported

(0x02) iconst_m1	Supported

(0x03) iconst_0		Supported

(0x04) iconst_1		Supported

(0x05) iconst_2		Supported

(0x06) iconst_3		Supported

(0x07) iconst_4		Supported

(0x08) iconst_5		Supported

(0x09) lconst_0		Not supported

(0x0a) lconst_1		Not supported

(0x0b) fconst_0		Not supported

(0x0c) fconst_1		Not supported

(0x0d) fconst_2		Not supported

(0x0e) dconst_0		Not supported

(0x0f) dconst_1		Not supported

(0x10) bipush		Supported

(0x11) sipush		Not supported

(0x12) ldc		Supported

(0x13) ldc_w		Not supported

(0x14) ldc2_w		Not supported

(0x15) iload		Not supported

(0x16) lload		Not supported

(0x17) fload		Not supported

(0x18) dload		Not supported

(0x19) aload		Not supported

(0x1a) iload_0		Supported

(0x1b) iload_1		Supported

(0x1c) iload_2		Supported

(0x1d) iload_3		Supported

(0x1e) lload_0		Not supported

(0x1f) lload_1		Not supported

(0x20) lload_2		Not supported

(0x21) lload_3		Not supported

(0x22) fload_0		Not supported

(0x23) fload_1		Not supported

(0x24) fload_2		Not supported

(0x25) fload_3		Not supported

(0x26) dload_0		Not supported

(0x27) dload_1		Not supported

(0x28) dload_2		Not supported

(0x29) dload_3		Not supported

(0x2a) aload_0		Not supported

(0x2b) aload_1		Not supported

(0x2c) aload_2		Not supported

(0x2d) aload_3		Not supported

(0x2e) iaload		Not supported

(0x2f) laload		Not supported

(0x30) faload		Not supported

(0x31) daload		Not supported

(0x32) aaload		Not supported

(0x33) baload		Not supported

(0x34) caload		Not supported

(0x35) saload		Not supported

(0x36) istore		Not supported

(0x37) lstore		Not supported

(0x38) fstore		Not supported

(0x39) dstore		Not supported

(0x3a) astore		Not supported

(0x3b) istore_0		Not supported

(0x3c) istore_1		Not supported

(0x3d) istore_2		Not supported

(0x3e) istore_3		Not supported

(0x3f) lstore_0		Not supported

(0x40) lstore_1		Not supported

(0x41) lstore_2		Not supported

(0x42) lstore_3		Not supported

(0x43) fstore_0		Not supported

(0x44) fstore_1		Not supported

(0x45) fstore_2		Not supported

(0x46) fstore_3		Not supported

(0x47) dstore_0		Not supported

(0x48) dstore_1		Not supported

(0x49) dstore_2		Not supported

(0x4a) dstore_3		Not supported

(0x4b) astore_0		Not supported

(0x4c) astore_1		Not supported

(0x4d) astore_2		Not supported

(0x4e) astore_3		Not supported

(0x4f) iastore		Not supported

(0x50) lastore		Not supported

(0x51) fastore		Not supported

(0x52) dastore		Not supported

(0x53) aastore		Not supported

(0x54) bastore		Not supported

(0x55) castore		Not supported

(0x56) sastore		Not supported

(0x57) pop		Not supported

(0x58) pop2		Not supported

(0x59) dup		Not supported

(0x5a) dup_x1		Not supported

(0x5b) dup_x2		Not supported

(0x5c) dup2		Not supported

(0x5d) dup2_x1		Not supported

(0x5e) dup2_x2		Not supported

(0x5f) swap		Not supported

(0x60) iadd		Supported

(0x61) ladd		Not supported

(0x62) fadd		Not supported

(0x63) dadd		Not supported

(0x64) isub		Supported

(0x65) lsub		Not supported

(0x66) fsub		Not supported

(0x67) dsub		Not supported

(0x68) imul		Supported

(0x69) lmul		Not supported

(0x6a) fmul		Not supported

(0x6b) dmul		Not supported

(0x6c) idiv		Supported

(0x6d) ldiv		Not supported

(0x6e) fdiv		Not supported

(0x6f) ddiv		Not supported

(0x70) irem		Supported

(0x71) lrem		Not supported

(0x72) frem		Not supported

(0x73) drem		Not supported

(0x74) ineg		Supported

(0x75) lneg		Not supported

(0x76) fneg		Not supported

(0x77) dneg		Not supported

(0x78) ishl		Supported

(0x79) lshl		Not supported

(0x7a) ishr		Supported

(0x7b) lshr		Not supported

(0x7c) iushr		Supported

(0x7d) lushr		Not supported

(0x7e) iand		Supported

(0x7f) land		Not supported

(0x80) ior		Supported

(0x81) lor		Not supported

(0x82) ixor		Supported

(0x83) lxor		Not supported

(0x84) iinc		Not supported

(0x85) i2l		Not supported

(0x86) i2f		Not supported

(0x87) i2d		Not supported

(0x88) l2i		Not supported

(0x89) l2f		Not supported

(0x8a) l2d		Not supported

(0x8b) f2i		Not supported

(0x8c) f2l		Not supported

(0x8d) f2d		Not supported

(0x8e) d2i		Not supported

(0x8f) d2l		Not supported

(0x90) d2f		Not supported

(0x91) i2b		Not supported

(0x92) i2c		Not supported

(0x93) i2s		Not supported

(0x94) lcmp		Not supported

(0x95) fcmpl		Not supported

(0x96) fcmpg		Not supported

(0x97) dcmpl		Not supported

(0x98) dcmpg		Not supported

(0x99) ifeq		Not supported

(0x9a) ifne		Not supported

(0x9b) iflt		Not supported

(0x9c) ifge		Not supported

(0x9d) ifgt		Not supported

(0x9e) ifle		Not supported

(0x9f) if_icmpeq	Not supported

(0xa0) if_icmpne	Not supported

(0xa1) if_icmplt	Not supported

(0xa2) if_icmpge	Not supported

(0xa3) if_icmpgt	Not supported

(0xa4) if_icmple	Not supported

(0xa5) if_acmpeq	Not supported

(0xa6) if_acmpne	Not supported

(0xa7) goto		Not supported

(0xa8) jsr		Not supported

(0xa9) ret		Not supported

(0xaa) tableswitch	Not supported

(0xab) lookupswitch	Not supported

(0xac) ireturn		Supported

(0xad) lreturn		Not supported

(0xae) freturn		Not supported

(0xaf) dreturn		Not supported

(0xb0) areturn		Not supported

(0xb1) return		Supported

(0xb2) getstatic	Not supported

(0xb3) putstatic	Not supported

(0xb4) getfield		Not supported

(0xb5) putfield		Not supported

(0xb6) invokevirtual	Partially supported

(0xb7) invokespecial	Not supported

(0xb8) invokestatic	Partially supported

(0xb9) invokeinterface	Not supported

(0xba) xxxunusedxxx1	Not supported

(0xbb) new		Not supported

(0xbc) newarray		Not supported

(0xbd) anewarray	Not supported

(0xbe) arraylength	Not supported

(0xbf) athrow		Not supported

(0xc0) checkcast	Not supported

(0xc1) instanceof	Not supported

(0xc2) monitorenter	Not supported

(0xc3) monitorexit	Not supported

(0xc4) wide		Not supported

(0xc5) multianewarray	Not supported

(0xc6) ifnull		Not supported

(0xc7) ifnonnull	Not supported

(0xc8) goto_w		Not supported

(0xc9) jsr_w		Not supported

 Reserved opcodes:

(0xca) breakpoint	Not supported	

(0xfe) impdep1		Not supported

(0xff) impdep2		Not supported
